GSL/__init__.py
GSL/experiment.py
GSL/metric.py
GSL/processor.py
GSL/utils.py
GSL/data/__init__.py
GSL/data/dataset.py
GSL/data/graph_dataset.py
GSL/data/hetero_dataset.py
GSL/encoder/__init__.py
GSL/encoder/gat.py
GSL/encoder/gcn.py
GSL/encoder/gin.py
GSL/encoder/graphsage.py
GSL/eval/__init__.py
GSL/eval/eval_cls.py
GSL/learner/__init__.py
GSL/learner/attention_learner.py
GSL/learner/base_learner.py
GSL/learner/full_param_learner.py
GSL/learner/gnn_learner.py
GSL/learner/hadamard_prod_learner.py
GSL/learner/mlp_learner.py
GSL/learner/sparsification_learner.py
GSL/model/__init__.py
GSL/model/base_gsl.py
GSL/model/cogsl.py
GSL/model/gen.py
GSL/model/grcn.py
GSL/model/gtn.py
GSL/model/hesgsl.py
GSL/model/hgpsl.py
GSL/model/hgsl.py
GSL/model/idgl.py
GSL/model/neuralsparse.py
GSL/model/prognn.py
GSL/model/ptdnet.py
GSL/model/slaps.py
GSL/model/stable.py
GSL/model/sublime.py
GSL/model/vibgsl.py
GSLB-0.1.0.dist-info/LICENSE
GSLB-0.1.0.dist-info/METADATA
GSLB-0.1.0.dist-info/WHEEL
GSLB-0.1.0.dist-info/top_level.txt
GSLB-0.1.0.dist-info/RECORD
