Metadata-Version: 2.1
Name: GSLB
Version: 0.1.0
Summary: GSLB: Graph Structure Learning Benchmark
Home-page: https://github.com/GSL-Benchmark/GSLB
Author: Liang Wang
Author-email: wangliang.leon20@gmail.com
Project-URL: Bug Tracker, https://github.com/GSL-Benchmark/GSLB/issues
Keywords: PyTorch,Graph-Neural-Networks,Graph-Structure-Learning
Classifier: Programming Language :: Python :: 3
Classifier: License :: OSI Approved :: MIT License
Classifier: Operating System :: OS Independent
Requires-Python: >=3.8
License-File: LICENSE
Requires-Dist: torch (>=1.13)
Requires-Dist: dgl (>=1.1)
Requires-Dist: numpy
Requires-Dist: scipy
Requires-Dist: networkx
Requires-Dist: scikit-learn
Requires-Dist: tqdm
Requires-Dist: ogb
Requires-Dist: easydict
Requires-Dist: PyYAML
